parsedoc/__init__.py
parsedoc/blocks.py
parsedoc/parser.py
parsedoc/plugins.py
parsedoc/utils.py
parsedoc-0.2.1.dist-info/DESCRIPTION.rst
parsedoc-0.2.1.dist-info/METADATA
parsedoc-0.2.1.dist-info/RECORD
parsedoc-0.2.1.dist-info/WHEEL
parsedoc-0.2.1.dist-info/entry_points.txt
parsedoc-0.2.1.dist-info/metadata.json
parsedoc-0.2.1.dist-info/top_level.txt
