Metadata-Version: 2.0
Name: parsedoc
Version: 0.2.1
Summary: Parses PHP doc blocks into markdown
Home-page: https://github.com/thomwiggers/parsedoc
Author: Thom Wiggers
Author-email: thom@thomwiggers.nl
License: 
Requires-Dist: docopt
